README.md
configly/__init__.py
configly/config.py
configly/interpolators/__init__.py
configly/interpolators/docker_secret.py
configly/interpolators/env.py
configly/interpolators/file.py
configly/interpolators/vault.py
configly/loaders.py
configly/process.py
configly/py.typed
configly/registry.py
configly/utilities.py
configly-1.0.0.dist-info/LICENSE
configly-1.0.0.dist-info/WHEEL
configly-1.0.0.dist-info/METADATA
configly-1.0.0.dist-info/RECORD
