Metadata-Version: 2.1
Name: configly
Version: 1.0.0
Summary: 
Home-page: https://github.com/schireson/configly
License: MIT
Keywords: config,yaml,toml,env
Author: Dan Cardin
Author-email: ddcardin@gmail.com
Requires-Python: >=3.6.2,<4
Classifier: License :: OSI Approved :: MIT License
Classifier: Programming Language :: Python :: 3
Classifier: Programming Language :: Python :: 3.10
Classifier: Programming Language :: Python :: 3.7
Classifier: Programming Language :: Python :: 3.8
Classifier: Programming Language :: Python :: 3.9
Provides-Extra: toml
Provides-Extra: tomli
Provides-Extra: vault
Provides-Extra: yaml
Requires-Dist: hvac; extra == "vault"
Requires-Dist: ruamel.yaml; extra == "yaml"
Requires-Dist: toml; extra == "toml"
Requires-Dist: tomli; extra == "tomli"
Project-URL: Repository, https://github.com/schireson/configly
